edx_rbac/__init__.py
edx_rbac/apps.py
edx_rbac/constants.py
edx_rbac/decorators.py
edx_rbac/fields.py
edx_rbac/mixins.py
edx_rbac/models.py
edx_rbac/urls.py
edx_rbac/utils.py
edx_rbac/admin/__init__.py
edx_rbac/admin/forms.py
edx_rbac/templates/edx_rbac/base.html
edx_rbac-2.1.0.dist-info/licenses/AUTHORS
edx_rbac-2.1.0.dist-info/licenses/LICENSE
edx_rbac-2.1.0.dist-info/licenses/LICENSE.txt
edx_rbac-2.1.0.dist-info/METADATA
edx_rbac-2.1.0.dist-info/WHEEL
edx_rbac-2.1.0.dist-info/top_level.txt
edx_rbac-2.1.0.dist-info/RECORD
